README.md
setup.py
py_mock.egg-info/PKG-INFO
py_mock.egg-info/SOURCES.txt
py_mock.egg-info/dependency_links.txt
py_mock.egg-info/requires.txt
py_mock.egg-info/top_level.txt
pymock/__init__.py
pymock/js/mock.mini_racer.min.js