Metadata-Version: 2.1
Name: py-mock
Version: 1.1.1
Summary: Mock.js for Python3
Home-page: https://github.com/mocobk/pymock
Author: mocobk
Author-email: mailmzb@qq.com
License: UNKNOWN
Keywords: pymock,Mock,Mock.js,better-mock
Platform: UNKNOWN
Classifier: Programming Language :: Python :: 3 :: Only
Classifier: Programming Language :: Python :: 3.6
Classifier: Programming Language :: Python :: 3.7
Classifier: Programming Language :: Python :: 3.8
Classifier: License :: OSI Approved :: MIT License
Classifier: Operating System :: OS Independent
